zlczh/__init__.py
zlczh/autoin.py
zlczh-0.0.1.dist-info/LICENSE
zlczh-0.0.1.dist-info/METADATA
zlczh-0.0.1.dist-info/WHEEL
zlczh-0.0.1.dist-info/top_level.txt
zlczh-0.0.1.dist-info/RECORD
