Metadata-Version: 2.1
Name: zlczh
Version: 0.0.1
Summary: publish AutoFormula to pypi.
Author: zlczh
Author-email: ervin42772@gmail.com
License: UNKNOWN
Platform: UNKNOWN
Classifier: Programming Language :: Python :: 3.7
Classifier: License :: OSI Approved :: MIT License
Classifier: Operating System :: OS Independent
License-File: LICENSE
